steampi/__init__.py
steampi/api.py
steampi/calendar.py
steampi/difflib_utils.py
steampi/json_utils.py
steampi/levenshtein_utils.py
steampi/text_distances.py
steampi/utils.py
steampi/tests/__init__.py
steampi/tests/test_api.py
steampi/tests/test_calendar.py
steampi/tests/test_difflib_utils.py
steampi/tests/test_json_utils.py
steampi/tests/test_levenshtein_utils.py
steampi/tests/test_text_distances.py
steampi/tests/test_utils.py
steampi-0.5.2.dist-info/LICENSE
steampi-0.5.2.dist-info/METADATA
steampi-0.5.2.dist-info/WHEEL
steampi-0.5.2.dist-info/top_level.txt
steampi-0.5.2.dist-info/RECORD
