Metadata-Version: 2.1
Name: steampi
Version: 0.5.2
Summary: Steam API on PyPI
Home-page: https://github.com/woctezuma/steampi
Author: Wok
Author-email: wok@tuta.io
License: UNKNOWN
Download-URL: https://github.com/woctezuma/steampi/archive/0.5.2.tar.gz
Keywords: steam,steamspy,api
Platform: UNKNOWN
Classifier: Development Status :: 4 - Beta
Classifier: Topic :: Games/Entertainment
Classifier: Programming Language :: Python :: 3
Classifier: License :: OSI Approved :: MIT License
Classifier: Operating System :: OS Independent
Requires-Python: >=3
Requires-Dist: python-Levenshtein
Requires-Dist: requests
Requires-Dist: steamspypi
